README.rst
setup.py
mac_address_switcher/__init__.py
mac_address_switcher/constants.py
mac_address_switcher/helpers.py
mac_address_switcher/menu.py
mac_address_switcher/version.py
mswitcher.egg-info/PKG-INFO
mswitcher.egg-info/SOURCES.txt
mswitcher.egg-info/dependency_links.txt
mswitcher.egg-info/entry_points.txt
mswitcher.egg-info/top_level.txt