Metadata-Version: 1.1
Name: mswitcher
Version: 0.1.4
Summary: Mac address switcher
Home-page: https://github.com/jeyraof/mac-address-switcher
Author: Jaeyoung Lee
Author-email: jaeyoung@monodiary.net
License: No license
Platform: UNKNOWN
Classifier: Development Status :: 3 - Alpha
Classifier: Environment :: Console
Classifier: Environment :: MacOS X
Classifier: Programming Language :: Python :: 2.6
Classifier: Programming Language :: Python :: 2.7
Classifier: Topic :: Utilities
